chinesename_feng-0.0.9.dist-info/METADATA
chinesename_feng-0.0.9.dist-info/RECORD
chinesename_feng-0.0.9.dist-info/WHEEL
chinesename_feng-0.0.9.dist-info/top_level.txt
example_pkg/__init__.py
