Metadata-Version: 2.1
Name: chinesename-feng
Version: 0.0.9
Summary: get a chinesename by random
Home-page: https://github.com/mouday/chinesename
Author: fengxiaochuan
Author-email: fengxiaochuan@corp.netease.com
License: MIT License
Platform: UNKNOWN
